mayutils/__init__.py
mayutils/core/__init__.py
mayutils/core/constants.py
mayutils/data/__init__.py
mayutils/data/analysis/__init__.py
mayutils/data/cache/.gitkeep
mayutils/data/live.py
mayutils/data/local.py
mayutils/data/queries/.gitkeep
mayutils/data/queries/__init__.py
mayutils/data/queries/examples/.gitkeep
mayutils/data/read.py
mayutils/environment/__init__.py
mayutils/environment/benchmarking.py
mayutils/environment/databases.py
mayutils/environment/filesystem.py
mayutils/environment/logging.py
mayutils/environment/memoisation.py
mayutils/environment/oauth.py
mayutils/environment/secrets.py
mayutils/environment/webdrivers.py
mayutils/export/__init__.py
mayutils/export/html.py
mayutils/export/images.py
mayutils/export/pdf.py
mayutils/export/slides.py
mayutils/interfaces/__init__.py
mayutils/interfaces/google.py
mayutils/interfaces/markdown.py
mayutils/interfaces/microsoft/__init__.py
mayutils/interfaces/microsoft/powerpoint/__init__.py
mayutils/interfaces/microsoft/powerpoint/markdown.py
mayutils/interfaces/microsoft.py
mayutils/interfaces/pdf.py
mayutils/interfaces/streamlit.py
mayutils/mathematics/__init__.py
mayutils/mathematics/numba.py
mayutils/mathematics/numpy.py
mayutils/objects/__init__.py
mayutils/objects/classes.py
mayutils/objects/colours.py
mayutils/objects/dataframes.py
mayutils/objects/datetime.py
mayutils/objects/decorators.py
mayutils/objects/dictionaries.py
mayutils/objects/functions.py
mayutils/objects/hashing.py
mayutils/objects/numbers.py
mayutils/objects/strings.py
mayutils/objects/types.py
mayutils/py.typed
mayutils/scripts/__init__.py
mayutils/scripts/clear_cache.py
mayutils/scripts/versioning.py
mayutils/testing/__init__.py
mayutils/visualisation/__init__.py
mayutils/visualisation/console.py
mayutils/visualisation/graphs/__init__.py
mayutils/visualisation/graphs/combine.py
mayutils/visualisation/graphs/matplotlib/__init__.py
mayutils/visualisation/graphs/matplotlib/template.py
mayutils/visualisation/graphs/plotly/__init__.py
mayutils-1.2.51.dist-info/WHEEL
mayutils-1.2.51.dist-info/entry_points.txt
mayutils-1.2.51.dist-info/METADATA
mayutils-1.2.51.dist-info/RECORD
