Metadata-Version: 2.3
Name: mayutils
Version: 1.2.51
Summary: Utilities for Python from Mayuran Visakan
Author: Mayuran Visakan
Author-email: Mayuran Visakan <mayuran.k.v@gmail.com>
License: MIT License
Requires-Dist: asyncer>=0.0.8
Requires-Dist: chromedriver-autoinstaller>=0.6.4
Requires-Dist: cookiecutter>=2.6.0
Requires-Dist: dataframe-image>=0.2.7
Requires-Dist: gitpython>=3.1.45
Requires-Dist: google-api-python-client>=2.179.0
Requires-Dist: google-auth>=2.40.3
Requires-Dist: google-auth-httplib2>=0.2.0
Requires-Dist: google-auth-oauthlib>=1.2.2
Requires-Dist: google-cloud-storage>=3.3.0
Requires-Dist: great-tables>=0.18.0
Requires-Dist: html2image>=2.0.7
Requires-Dist: ipykernel>=6.30.1
Requires-Dist: itables>=2.4.5
Requires-Dist: jupysql>=0.11.1
Requires-Dist: jupyter>=1.1.1
Requires-Dist: kaleido>=1.0.0
Requires-Dist: keyring>=25.6.0
Requires-Dist: markdown
Requires-Dist: matplotlib>=3.10.5
Requires-Dist: mistune>=3.2.0
Requires-Dist: modin[all]>=0.35.0
Requires-Dist: nbconvert>=7.16.6
Requires-Dist: numba>=0.62.0rc1
Requires-Dist: numpy>=2.3.2
Requires-Dist: numpy-financial>=1.0.0
Requires-Dist: openpyxl>=3.1.5
Requires-Dist: pandas>=2.3.2
Requires-Dist: pandas-stubs>=2.3.2.250827
Requires-Dist: pathlib>=1.0.1
Requires-Dist: pendulum[test]>=3.1.0
Requires-Dist: pillow>=11.3.0
Requires-Dist: playwright>=1.55.0
Requires-Dist: plotly>=6.3.0
Requires-Dist: polars>=1.32.3
Requires-Dist: pre-commit>=4.3.0
Requires-Dist: pyarrow>=21.0.0
Requires-Dist: pydantic>=2.11.7
Requires-Dist: pydantic-settings>=2.10.1
Requires-Dist: pymupdf>=1.26.4
Requires-Dist: pytest>=8.4.2
Requires-Dist: python-dotenv>=1.1.1
Requires-Dist: python-pptx>=1.0.2
Requires-Dist: requests>=2.32.5
Requires-Dist: rich>=14.1.0
Requires-Dist: scikit-learn>=1.7.1
Requires-Dist: scipy>=1.16.1
Requires-Dist: scipy-stubs>=1.16.2.4
Requires-Dist: selenium>=4.35.0
Requires-Dist: snowflake-connector-python[secure-local-storage]>=3.17.2
Requires-Dist: snowflake-sqlalchemy>=1.7.6
Requires-Dist: sqlalchemy>=2.0.43
Requires-Dist: streamlit>=1.49.0
Requires-Dist: typer
Requires-Dist: types-cachetools>=6.2.0.20251022
Requires-Dist: types-decorator>=5.2.0.20250324
Requires-Dist: types-markdown>=3.10.0.20251106
Requires-Dist: types-openpyxl>=3.1.5.20250919
Requires-Dist: types-pycurl>=7.45.7.20250926
Requires-Dist: types-python-dateutil>=2.9.0.20251008
Requires-Dist: types-pyyaml>=6.0.12.20250915
Requires-Dist: types-requests>=2.32.4.20250913
Requires-Dist: types-simplejson>=3.20.0.20250822
Requires-Dist: types-six>=1.17.0.20250515
Requires-Dist: types-toml>=0.10.8.20240310
Requires-Dist: unicodeit>=0.7.5
Requires-Dist: watchdog>=6.0.0
Requires-Dist: coverage ; extra == 'dev'
Requires-Dist: pytest ; extra == 'dev'
Requires-Dist: ruff ; extra == 'dev'
Requires-Dist: ty ; extra == 'dev'
Requires-Dist: mypy ; extra == 'dev'
Requires-Dist: ipdb ; extra == 'dev'
Maintainer: Mayuran Visakan
Maintainer-email: Mayuran Visakan <mayuran.k.v@gmail.com>
Requires-Python: >=3.12, <4.0
Provides-Extra: dev
